<?xml version="1.0" encoding="UTF-8"?>
<vivadoHLSLog:LogRoot xmlns:vivadoHLSLog="www.xilinx.com/vivadoHLSLog">
  <errorLogs>
    <logs>
      <synLog/>
      <simLog/>
      <mgLog/>
      <packageLog/>
      <csimLog/>
    </logs>
  </errorLogs>
  <warningLogs>
    <logs>
      <synLog/>
      <simLog>
        <logs message="WARNING: [VRFC 10-982] library name floating_point_v7_1_4 of instantiated unit conflicts with visible identifier [ip/xil_defaultlib/simple_ap_fadd_3_full_dsp_32.vhd:189]&#xA;Completed static elaboration&#xA;Starting simulation data flow analysis&#xA;Completed simulation data flow analysis&#xA;Time Resolution for simulation is 1ps&#xA;Compiling package std.standard&#xA;Compiling package std.textio&#xA;Compiling package ieee.std_logic_1164&#xA;Compiling package ieee.std_logic_arith&#xA;Compiling package ieee.std_logic_unsigned&#xA;Compiling package ieee.numeric_std&#xA;Compiling package ieee.std_logic_textio&#xA;Compiling package floating_point_v7_1_4.floating_point_v7_1_4_viv_comp&#xA;Compiling package xbip_utils_v3_0_7.xbip_utils_v3_0_7_pkg&#xA;Compiling package axi_utils_v2_0_3.axi_utils_v2_0_3_pkg&#xA;Compiling package floating_point_v7_1_4.floating_point_v7_1_4_consts&#xA;Compiling package ieee.math_real&#xA;Compiling package floating_point_v7_1_4.floating_point_v7_1_4_exp_table_...&#xA;Compiling package mult_gen_v12_0_12.mult_gen_v12_0_12_pkg&#xA;Compiling package ieee.std_logic_signed&#xA;Compiling package floating_point_v7_1_4.floating_point_v7_1_4_pkg&#xA;Compiling package floating_point_v7_1_4.flt_utils&#xA;Compiling package xbip_pipe_v3_0_3.xbip_pipe_v3_0_3_viv_comp&#xA;Compiling package unisim.vcomponents&#xA;Compiling package ieee.vital_timing&#xA;Compiling package ieee.vital_primitives&#xA;Compiling package unisim.vpkg&#xA;Compiling architecture muxcy_v of entity unisim.MUXCY [muxcy_default]&#xA;Compiling architecture synth of entity xbip_pipe_v3_0_3.xbip_pipe_v3_0_3_viv [\xbip_pipe_v3_0_3_viv(c_has_ce=1...]&#xA;Compiling architecture rtl of entity floating_point_v7_1_4.delay [\delay(width=7,length=0)\]&#xA;Compiling architecture struct of entity floating_point_v7_1_4.carry_chain [\carry_chain(c_xdevicefamily=&quot;ar...]&#xA;Compiling architecture synth of entity floating_point_v7_1_4.compare_eq_im [\compare_eq_im(c_xdevicefamily=&quot;...]&#xA;Compiling architecture xorcy_v of entity unisim.XORCY [xorcy_default]&#xA;Compiling architecture struct of entity floating_point_v7_1_4.carry_chain [\carry_chain(c_xdevicefamily=&quot;ar...]&#xA;Compiling architecture synth of entity xbip_pipe_v3_0_3.xbip_pipe_v3_0_3_viv [\xbip_pipe_v3_0_3_viv(c_has_ce=1...]&#xA;Compiling architecture rtl of entity floating_point_v7_1_4.delay [\delay(length=0)\]&#xA;Compiling architecture synth of entity xbip_pipe_v3_0_3.xbip_pipe_v3_0_3_viv [\xbip_pipe_v3_0_3_viv(c_has_ce=1...]&#xA;Compiling architecture rtl of entity floating_point_v7_1_4.delay [\delay(width=24,length=0,fast_in...]&#xA;Compiling architecture synth of entity xbip_pipe_v3_0_3.xbip_pipe_v3_0_3_viv [\xbip_pipe_v3_0_3_viv(c_has_ce=1...]&#xA;Compiling architecture rtl of entity floating_point_v7_1_4.delay [\delay(width=16,length=0)\]&#xA;Compiling architecture synth of entity xbip_pipe_v3_0_3.xbip_pipe_v3_0_3_viv [\xbip_pipe_v3_0_3_viv(c_has_ce=1...]&#xA;Compiling architecture rtl of entity floating_point_v7_1_4.delay [\delay(width=4,length=0)\]&#xA;Compiling architecture synth of entity xbip_pipe_v3_0_3.xbip_pipe_v3_0_3_viv [\xbip_pipe_v3_0_3_viv(c_has_ce=1...]&#xA;Compiling architecture rtl of entity floating_point_v7_1_4.delay [\delay(width=48,length=0)\]&#xA;Compiling architecture synth of entity xbip_pipe_v3_0_3.xbip_pipe_v3_0_3_viv [\xbip_pipe_v3_0_3_viv(c_has_ce=1...]&#xA;Compiling architecture rtl of entity floating_point_v7_1_4.delay [\delay(width=24,length=0)\]&#xA;Compiling architecture dsp48e1_v of entity unisim.DSP48E1 [\DSP48E1(acascreg=0,adreg=0,alum...]&#xA;Compiling architecture rtl of entity floating_point_v7_1_4.dsp48e1_wrapper [\dsp48e1_wrapper(a_width=24,c_wi...]&#xA;Compiling architecture synth of entity xbip_pipe_v3_0_3.xbip_pipe_v3_0_3_viv [\xbip_pipe_v3_0_3_viv(c_latency=...]&#xA;Compiling architecture rtl of entity floating_point_v7_1_4.delay [delay_default]&#xA;Compiling architecture synth of entity xbip_pipe_v3_0_3.xbip_pipe_v3_0_3_viv [\xbip_pipe_v3_0_3_viv(c_has_ce=1...]&#xA;Compiling architecture rtl of entity floating_point_v7_1_4.delay [\delay(width=13,length=0)\]&#xA;Compiling architecture synth of entity xbip_pipe_v3_0_3.xbip_pipe_v3_0_3_viv [\xbip_pipe_v3_0_3_viv(c_has_ce=1...]&#xA;Compiling architecture rtl of entity floating_point_v7_1_4.delay [\delay(width=27,length=0)\]&#xA;Compiling architecture synth of entity floating_point_v7_1_4.align_add_dsp48e1_sgl [\align_add_dsp48e1_sgl(c_xdevice...]&#xA;Compiling architecture lut5_v of entity unisim.LUT5 [\LUT5(init=&quot;00000000000000001111...]&#xA;Compiling architecture lut5_v of entity unisim.LUT5 [\LUT5(init=&quot;00000000000000000000...]&#xA;Compiling architecture synth of entity xbip_pipe_v3_0_3.xbip_pipe_v3_0_3_viv [\xbip_pipe_v3_0_3_viv(c_has_ce=1...]&#xA;Compiling architecture rtl of entity floating_point_v7_1_4.delay [\delay(width=5,length=0)\]&#xA;Compiling architecture rtl of entity floating_point_v7_1_4.lead_zero_encode_shift [\lead_zero_encode_shift(ab_fw=24...]&#xA;Compiling architecture synth of entity xbip_pipe_v3_0_3.xbip_pipe_v3_0_3_viv [\xbip_pipe_v3_0_3_viv(c_has_ce=1...]&#xA;Compiling architecture rtl of entity floating_point_v7_1_4.delay [\delay(width=3,length=0)\]&#xA;Compiling architecture lut6_v of entity unisim.LUT6 [\LUT6(init=&quot;11111110010101001011...]&#xA;Compiling architecture lut5_v of entity unisim.LUT5 [\LUT5(init=&quot;00010001010111110000...]&#xA;Compiling architecture lut5_v of entity unisim.LUT5 [\LUT5(init=&quot;11101110101000001111...]&#xA;Compiling architecture synth of entity xbip_pipe_v3_0_3.xbip_pipe_v3_0_3_viv [\xbip_pipe_v3_0_3_viv(c_latency=...]&#xA;Compiling architecture rtl of entity floating_point_v7_1_4.delay [\delay(width=2)\]&#xA;Compiling architecture synth of entity xbip_pipe_v3_0_3.xbip_pipe_v3_0_3_viv [\xbip_pipe_v3_0_3_viv(c_has_ce=1...]&#xA;Compiling architecture rtl of entity floating_point_v7_1_4.delay [\delay(width=25,length=0)\]&#xA;Compiling architecture dsp48e1_v of entity unisim.DSP48E1 [\DSP48E1(adreg=0,alumodereg=0,ca...]&#xA;Compiling architecture rtl of entity floating_point_v7_1_4.dsp48e1_wrapper [\dsp48e1_wrapper(a_width=24,c_wi...]&#xA;Compiling architecture rtl of entity floating_point_v7_1_4.norm_and_round_dsp48e1_sgl [\norm_and_round_dsp48e1_sgl(c_mu...]&#xA;Compiling architecture lut5_v of entity unisim.LUT5 [\LUT5(init=&quot;10011001100110011001...]&#xA;Compiling architecture lut5_v of entity unisim.LUT5 [\LUT5(init=&quot;11111111000000001111...]&#xA;Compiling architecture synth of entity xbip_pipe_v3_0_3.xbip_pipe_v3_0_3_viv [\xbip_pipe_v3_0_3_viv(c_has_ce=1...]&#xA;Compiling architecture rtl of entity floating_point_v7_1_4.delay [\delay(width=9,length=0)\]&#xA;Compiling architecture struct of entity floating_point_v7_1_4.carry_chain [\carry_chain(c_xdevicefamily=&quot;ar...]&#xA;Compiling architecture synth of entity xbip_pipe_v3_0_3.xbip_pipe_v3_0_3_viv [\xbip_pipe_v3_0_3_viv(c_has_ce=1...]&#xA;Compiling architecture rtl of entity floating_point_v7_1_4.delay [\delay(width=8,length=0)\]&#xA;Compiling architecture synth of entity xbip_pipe_v3_0_3.xbip_pipe_v3_0_3_viv [\xbip_pipe_v3_0_3_viv(c_latency=...]&#xA;Compiling architecture rtl of entity floating_point_v7_1_4.delay [\delay(width=10)\]&#xA;Compiling architecture synth of entity xbip_pipe_v3_0_3.xbip_pipe_v3_0_3_viv [\xbip_pipe_v3_0_3_viv(c_has_ce=1...]&#xA;Compiling architecture rtl of entity floating_point_v7_1_4.delay [\delay(width=4,length=0,fast_inp...]&#xA;Compiling architecture fdre_v of entity unisim.FDRE [fdre_default]&#xA;Compiling architecture fde_v of entity unisim.FDE [fde_default]&#xA;Compiling architecture struct of entity floating_point_v7_1_4.carry_chain [\carry_chain(c_xdevicefamily=&quot;ar...]&#xA;Compiling architecture synth of entity floating_point_v7_1_4.compare_eq_im [\compare_eq_im(c_xdevicefamily=&quot;...]&#xA;Compiling architecture synth of entity xbip_pipe_v3_0_3.xbip_pipe_v3_0_3_viv [\xbip_pipe_v3_0_3_viv(c_latency=...]&#xA;Compiling architecture rtl of entity floating_point_v7_1_4.delay [\delay(fast_input=true)\]&#xA;Compiling architecture rtl of entity floating_point_v7_1_4.special_detect [\special_detect(c_xdevicefamily=...]&#xA;Compiling architecture struct of entity floating_point_v7_1_4.carry_chain [\carry_chain(c_xdevicefamily=&quot;ar...]&#xA;Compiling architecture synth of entity floating_point_v7_1_4.compare_gt [\compare_gt(c_xdevicefamily=&quot;art...]&#xA;Compiling architecture synth of entity floating_point_v7_1_4.compare [\compare(c_xdevicefamily=&quot;artix7...]&#xA;Compiling architecture synth of entity xbip_pipe_v3_0_3.xbip_pipe_v3_0_3_viv [\xbip_pipe_v3_0_3_viv(c_latency=...]&#xA;Compiling architecture rtl of entity floating_point_v7_1_4.delay [\delay(width=8)\]&#xA;Compiling architecture synth of entity xbip_pipe_v3_0_3.xbip_pipe_v3_0_3_viv [\xbip_pipe_v3_0_3_viv(c_latency=...]&#xA;Compiling architecture rtl of entity floating_point_v7_1_4.delay [\delay(width=9)\]&#xA;Compiling architecture synth of entity xbip_pipe_v3_0_3.xbip_pipe_v3_0_3_viv [\xbip_pipe_v3_0_3_viv(c_latency=...]&#xA;Compiling architecture rtl of entity floating_point_v7_1_4.delay [\delay(width=2,length=2,fast_inp...]&#xA;Compiling architecture synth of entity xbip_pipe_v3_0_3.xbip_pipe_v3_0_3_viv [\xbip_pipe_v3_0_3_viv(c_latency=...]&#xA;Compiling architecture rtl of entity floating_point_v7_1_4.delay [\delay(length=2,fast_input=true)...]&#xA;Compiling architecture synth of entity xbip_pipe_v3_0_3.xbip_pipe_v3_0_3_viv [\xbip_pipe_v3_0_3_viv(c_has_ce=1...]&#xA;Compiling architecture rtl of entity floating_point_v7_1_4.delay [\delay(length=0,fast_input=true)...]&#xA;Compiling architecture synth of entity xbip_pipe_v3_0_3.xbip_pipe_v3_0_3_viv [\xbip_pipe_v3_0_3_viv(c_has_ce=1...]&#xA;Compiling architecture rtl of entity floating_point_v7_1_4.delay [\delay(width=2,length=0,fast_inp...]&#xA;Compiling architecture synth of entity xbip_pipe_v3_0_3.xbip_pipe_v3_0_3_viv [\xbip_pipe_v3_0_3_viv(c_has_ce=1...]&#xA;Compiling architecture rtl of entity floating_point_v7_1_4.delay [\delay(width=12,length=0)\]&#xA;Compiling architecture rtl of entity floating_point_v7_1_4.flt_add_exp_sp [\flt_add_exp_sp(c_xdevicefamily=...]&#xA;Compiling architecture synth of entity xbip_pipe_v3_0_3.xbip_pipe_v3_0_3_viv [\xbip_pipe_v3_0_3_viv(c_latency=...]&#xA;Compiling architecture rtl of entity floating_point_v7_1_4.delay [\delay(width=23)\]&#xA;Compiling architecture synth of entity floating_point_v7_1_4.flt_dec_op [\flt_dec_op(c_xdevicefamily=&quot;art...]&#xA;Compiling architecture rtl of entity floating_point_v7_1_4.flt_add_dsp [\flt_add_dsp(c_xdevicefamily=&quot;ar...]&#xA;Compiling architecture rtl of entity floating_point_v7_1_4.flt_add [\flt_add(c_xdevicefamily=&quot;artix7...]&#xA;Compiling architecture synth of entity xbip_pipe_v3_0_3.xbip_pipe_v3_0_3_viv [\xbip_pipe_v3_0_3_viv(c_latency=...]&#xA;Compiling architecture synth of entity xbip_pipe_v3_0_3.xbip_pipe_v3_0_3_viv [\xbip_pipe_v3_0_3_viv(c_has_ce=1...]&#xA;Compiling architecture rtl of entity floating_point_v7_1_4.delay [\delay(width=32,length=0)\]&#xA;Compiling architecture xilinx of entity floating_point_v7_1_4.floating_point_v7_1_4_viv [\floating_point_v7_1_4_viv(c_xde...]&#xA;Compiling architecture xilinx of entity floating_point_v7_1_4.floating_point_v7_1_4 [\floating_point_v7_1_4(c_xdevice...]&#xA;Compiling architecture simple_ap_fadd_3_full_dsp_32_arch of entity xil_defaultlib.simple_ap_fadd_3_full_dsp_32 [simple_ap_fadd_3_full_dsp_32_def...]&#xA;Compiling architecture arch of entity xil_defaultlib.simple_fadd_32ns_bkb [simple_fadd_32ns_bkb_default]&#xA;Compiling architecture behav of entity xil_defaultlib.simple [simple_default]&#xA;Compiling architecture behav of entity xil_defaultlib.AESL_automem_a [aesl_automem_a_default]&#xA;Compiling architecture behav of entity xil_defaultlib.AESL_automem_b [aesl_automem_b_default]&#xA;Compiling architecture behav of entity xil_defaultlib.AESL_automem_c [aesl_automem_c_default]&#xA;Compiling architecture behav of entity xil_defaultlib.apatb_simple_top&#xA;Built simulation snapshot simple&#xA;&#xA;&#xA;****** Webtalk v2017.2 (64-bit)&#xA;  **** SW Build 1909853 on Thu Jun 15 18:39:10 MDT 2017&#xA;  **** IP Build 1909766 on Thu Jun 15 19:58:00 MDT 2017&#xA;    ** Copyright 1986-2017 Xilinx, Inc. All Rights Reserved.&#xA;&#xA;&#xA;source /opt/Xilinx/Vivado_HLS/2017.2/bin/sequence_1_8_march/solution1/sim/vhdl/xsim.dir/simple/webtalk/xsim_webtalk.tcl -notrace" projectName="sequence_1_8_march" solutionName="solution1" date="2018-03-08T11:51:48.910+0530" type="Warning"/>
        <logs message="WARNING: [VRFC 10-1303] range is empty (null range) [/wrk/2017.2/nightly/2017_06_15_1909853/packages/customer/vivado/data/ip/xilinx/floating_point_v7_1/hdl/floating_point_v7_1_vh_rfs.vhd:13629]" projectName="sequence_1_8_march" solutionName="solution1" date="2018-03-08T11:51:40.818+0530" type="Warning"/>
        <logs message="WARNING: [VRFC 10-1303] range is empty (null range) [/wrk/2017.2/nightly/2017_06_15_1909853/packages/customer/vivado/data/ip/xilinx/floating_point_v7_1/hdl/floating_point_v7_1_vh_rfs.vhd:12604]" projectName="sequence_1_8_march" solutionName="solution1" date="2018-03-08T11:51:40.813+0530" type="Warning"/>
        <logs message="WARNING: [VRFC 10-1303] range is empty (null range) [/wrk/2017.2/nightly/2017_06_15_1909853/packages/customer/vivado/data/ip/xilinx/floating_point_v7_1/hdl/floating_point_v7_1_vh_rfs.vhd:12604]" projectName="sequence_1_8_march" solutionName="solution1" date="2018-03-08T11:51:40.607+0530" type="Warning"/>
        <logs message="WARNING: [VRFC 10-1303] range is empty (null range) [/wrk/2017.2/nightly/2017_06_15_1909853/packages/customer/vivado/data/ip/xilinx/floating_point_v7_1/hdl/floating_point_v7_1_vh_rfs.vhd:12604]" projectName="sequence_1_8_march" solutionName="solution1" date="2018-03-08T11:51:40.603+0530" type="Warning"/>
        <logs message="WARNING: [VRFC 10-1303] range is empty (null range) [/wrk/2017.2/nightly/2017_06_15_1909853/packages/customer/vivado/data/ip/xilinx/floating_point_v7_1/hdl/floating_point_v7_1_vh_rfs.vhd:12604]" projectName="sequence_1_8_march" solutionName="solution1" date="2018-03-08T11:51:40.598+0530" type="Warning"/>
        <logs message="WARNING: [VRFC 10-1303] range is empty (null range) [/wrk/2017.2/nightly/2017_06_15_1909853/packages/customer/vivado/data/ip/xilinx/xbip_pipe_v3_0/hdl/xbip_pipe_v3_0_vh_rfs.vhd:375]" projectName="sequence_1_8_march" solutionName="solution1" date="2018-03-08T11:51:40.593+0530" type="Warning"/>
        <logs message="WARNING: [VRFC 10-1303] range is empty (null range) [/wrk/2017.2/nightly/2017_06_15_1909853/packages/customer/vivado/data/ip/xilinx/xbip_pipe_v3_0/hdl/xbip_pipe_v3_0_vh_rfs.vhd:375]" projectName="sequence_1_8_march" solutionName="solution1" date="2018-03-08T11:51:40.589+0530" type="Warning"/>
        <logs message="WARNING: [VRFC 10-1303] range is empty (null range) [/wrk/2017.2/nightly/2017_06_15_1909853/packages/customer/vivado/data/ip/xilinx/xbip_pipe_v3_0/hdl/xbip_pipe_v3_0_vh_rfs.vhd:375]" projectName="sequence_1_8_march" solutionName="solution1" date="2018-03-08T11:51:40.581+0530" type="Warning"/>
        <logs message="WARNING: [VRFC 10-1303] range is empty (null range) [/wrk/2017.2/nightly/2017_06_15_1909853/packages/customer/vivado/data/ip/xilinx/xbip_pipe_v3_0/hdl/xbip_pipe_v3_0_vh_rfs.vhd:375]" projectName="sequence_1_8_march" solutionName="solution1" date="2018-03-08T11:51:40.568+0530" type="Warning"/>
        <logs message="WARNING: [VRFC 10-1303] range is empty (null range) [/wrk/2017.2/nightly/2017_06_15_1909853/packages/customer/vivado/data/ip/xilinx/xbip_pipe_v3_0/hdl/xbip_pipe_v3_0_vh_rfs.vhd:375]" projectName="sequence_1_8_march" solutionName="solution1" date="2018-03-08T11:51:40.562+0530" type="Warning"/>
        <logs message="WARNING: [VRFC 10-1303] range is empty (null range) [/wrk/2017.2/nightly/2017_06_15_1909853/packages/customer/vivado/data/ip/xilinx/xbip_pipe_v3_0/hdl/xbip_pipe_v3_0_vh_rfs.vhd:375]" projectName="sequence_1_8_march" solutionName="solution1" date="2018-03-08T11:51:40.449+0530" type="Warning"/>
        <logs message="WARNING: [VRFC 10-1303] range is empty (null range) [/wrk/2017.2/nightly/2017_06_15_1909853/packages/customer/vivado/data/ip/xilinx/floating_point_v7_1/hdl/floating_point_v7_1_vh_rfs.vhd:12604]" projectName="sequence_1_8_march" solutionName="solution1" date="2018-03-08T11:51:40.364+0530" type="Warning"/>
        <logs message="WARNING: [VRFC 10-1303] range is empty (null range) [/wrk/2017.2/nightly/2017_06_15_1909853/packages/customer/vivado/data/ip/xilinx/floating_point_v7_1/hdl/floating_point_v7_1_vh_rfs.vhd:12604]" projectName="sequence_1_8_march" solutionName="solution1" date="2018-03-08T11:51:40.189+0530" type="Warning"/>
        <logs message="WARNING: [VRFC 10-1303] range is empty (null range) [/wrk/2017.2/nightly/2017_06_15_1909853/packages/customer/vivado/data/ip/xilinx/xbip_pipe_v3_0/hdl/xbip_pipe_v3_0_vh_rfs.vhd:375]" projectName="sequence_1_8_march" solutionName="solution1" date="2018-03-08T11:51:40.185+0530" type="Warning"/>
        <logs message="WARNING: [VRFC 10-1303] range is empty (null range) [/wrk/2017.2/nightly/2017_06_15_1909853/packages/customer/vivado/data/ip/xilinx/floating_point_v7_1/hdl/floating_point_v7_1_vh_rfs.vhd:90362]" projectName="sequence_1_8_march" solutionName="solution1" date="2018-03-08T11:51:40.091+0530" type="Warning"/>
        <logs message="WARNING: [VRFC 10-1303] range is empty (null range) [/wrk/2017.2/nightly/2017_06_15_1909853/packages/customer/vivado/data/ip/xilinx/mult_gen_v12_0/hdl/mult_gen_v12_0_vh_rfs.vhd:2240]" projectName="sequence_1_8_march" solutionName="solution1" date="2018-03-08T11:51:39.872+0530" type="Warning"/>
        <logs message="WARNING: [VRFC 10-1303] range is empty (null range) [/wrk/2017.2/nightly/2017_06_15_1909853/packages/customer/vivado/data/ip/xilinx/mult_gen_v12_0/hdl/mult_gen_v12_0_vh_rfs.vhd:2255]" projectName="sequence_1_8_march" solutionName="solution1" date="2018-03-08T11:51:39.000+0530" type="Warning"/>
        <logs message="WARNING: [XSIM 43-3431] One or more environment variables have been detected which affect the operation of the C compiler. These are typically not set in standard installations and are not tested by Xilinx, however they may be appropriate for your system, so the flow will attempt to continue.  If errors occur, try running fuse with the &quot;-mt off -v 1&quot; switches to see more information from the C compiler. The following environment variables have been detected:&#xA;    LIBRARY_PATH" projectName="sequence_1_8_march" solutionName="solution1" date="2018-03-08T11:51:36.442+0530" type="Warning"/>
      </simLog>
      <mgLog/>
      <packageLog>
        <logs message="WARNING: [IP_Flow 19-4832] The IP name 'simple_ap_fadd_3_full_dsp_32' you have specified is long. The Windows operating system has path length limitations. It is recommended you use shorter names to reduce the likelihood of issues." projectName="sequence_1_8_march" solutionName="solution1" date="2018-03-08T12:13:00.320+0530" type="Warning"/>
        <logs message="WARNING: [IP_Flow 19-4832] The IP name 'simple_ap_fadd_3_full_dsp_32' you have specified is long. The Windows operating system has path length limitations. It is recommended you use shorter names to reduce the likelihood of issues." projectName="sequence_1_8_march" solutionName="solution1" date="2018-03-08T11:52:42.871+0530" type="Warning"/>
      </packageLog>
      <csimLog/>
    </logs>
  </warningLogs>
</vivadoHLSLog:LogRoot>
